firsthello/__init__.py
firsthello-0.1.dist-info/METADATA
firsthello-0.1.dist-info/WHEEL
firsthello-0.1.dist-info/top_level.txt
firsthello-0.1.dist-info/RECORD
