Metadata-Version: 2.1
Name: firsthello
Version: 0.1
Summary: This module greets the user.  
Home-page: UNKNOWN
Author: Mona 
Author-email: mvkatkar@yahoo.com
License: MIT
Platform: UNKNOWN
